pypegasus/__init__.py
pypegasus/logger.conf
pypegasus/pgclient.py
pypegasus/base/__init__.py
pypegasus/base/constants.py
pypegasus/base/ttypes.py
pypegasus/operate/__init__.py
pypegasus/operate/packet.py
pypegasus/replication/__init__.py
pypegasus/replication/constants.py
pypegasus/replication/replication.py
pypegasus/replication/ttypes.py
pypegasus/rrdb/__init__.py
pypegasus/rrdb/constants.py
pypegasus/rrdb/meta.py
pypegasus/rrdb/rrdb.py
pypegasus/rrdb/ttypes.py
pypegasus/transport/__init__.py
pypegasus/transport/compat.py
pypegasus/transport/protocol.py
pypegasus/utils/__init__.py
pypegasus/utils/tools.py
tests/__init__.py
tests/test_basics.py
tests/test_benchmark.py
tests/test_integration.py
pypegasus-0.1.17.dist-info/LICENSE
pypegasus-0.1.17.dist-info/METADATA
pypegasus-0.1.17.dist-info/WHEEL
pypegasus-0.1.17.dist-info/top_level.txt
pypegasus-0.1.17.dist-info/RECORD
