Metadata-Version: 2.1
Name: pypegasus
Version: 0.1.17
Summary: python client for xiaomi/pegasus
Home-page: https://github.com/XiaoMi/pegasus-python-client
Author: Lai Yingchun
Author-email: laiyingchun@xiaomi.com
License: Apache License 2.0
Platform: any
Classifier: Development Status :: 4 - Beta
Classifier: Operating System :: OS Independent
Classifier: Intended Audience :: Developers
Classifier: License :: OSI Approved :: Apache Software License
Classifier: Programming Language :: Python
Classifier: Programming Language :: Python :: Implementation
Classifier: Programming Language :: Python :: 2
Classifier: Topic :: Software Development :: Libraries
Requires-Dist: Automat (==0.3.0)
Requires-Dist: aenum (==2.0.9)
Requires-Dist: constantly (==15.1)
Requires-Dist: cryptography (==2.1.4)
Requires-Dist: hyperlink (==17.1.1)
Requires-Dist: idna (==2.1)
Requires-Dist: incremental (==21.3.0)
Requires-Dist: pyopenssl (==17.5.0)
Requires-Dist: thrift (==0.9.3)
Requires-Dist: twisted (==17.9.0)
Requires-Dist: zope.interface (==3.6.0)
